QST/MLE.py
QST/QSim.py
QST/__init__.py
QST-0.1.1.dist-info/LICENSE
QST-0.1.1.dist-info/METADATA
QST-0.1.1.dist-info/WHEEL
QST-0.1.1.dist-info/top_level.txt
QST-0.1.1.dist-info/RECORD
