Metadata-Version: 2.1
Name: QST
Version: 0.1.1
Summary: A package to perform Quantum State Tomography
Home-page: https://github.com/WilliamBidle/Quantum-State-Tomography
Author: William Bidle
Author-email: wkb15@scarletmail.rutgers.edu
Project-URL: Bug Tracker, https://github.com/WilliamBidle/Quantum-State-Tomography/issues
Classifier: Programming Language :: Python :: 3
Classifier: License :: OSI Approved :: MIT License
Classifier: Operating System :: OS Independent
Requires-Python: >=3.6
License-File: LICENSE
